mogui/__init__.py
mogui/__main__.py
mogui/modules.py
mogui/qtgui.py
mogui/setup_env.py
mogui/utils.py
mogui/icons/mogui-dark/index.theme
mogui/icons/mogui-dark/symbolic/actions/application-exit-symbolic.svg
mogui/icons/mogui-dark/symbolic/actions/document-revert-symbolic.svg
mogui/icons/mogui-dark/symbolic/actions/document-save-symbolic.svg
mogui/icons/mogui-dark/symbolic/actions/edit-clear-symbolic.svg
mogui/icons/mogui-dark/symbolic/actions/edit-undo-symbolic.svg
mogui/icons/mogui-dark/symbolic/actions/help-contents-symbolic.svg
mogui/icons/mogui-dark/symbolic/apps/environment-modules.svg
mogui/icons/mogui-light/index.theme
mogui/icons/mogui-light/symbolic/actions/application-exit-symbolic.svg
mogui/icons/mogui-light/symbolic/actions/document-revert-symbolic.svg
mogui/icons/mogui-light/symbolic/actions/document-save-symbolic.svg
mogui/icons/mogui-light/symbolic/actions/edit-clear-symbolic.svg
mogui/icons/mogui-light/symbolic/actions/edit-undo-symbolic.svg
mogui/icons/mogui-light/symbolic/actions/help-contents-symbolic.svg
mogui/icons/mogui-light/symbolic/apps/environment-modules.svg
modules_gui-0.2.2.dist-info/COPYING-ICONS.CCBYSA3
modules_gui-0.2.2.dist-info/COPYING.GPLv2
modules_gui-0.2.2.dist-info/METADATA
modules_gui-0.2.2.dist-info/WHEEL
modules_gui-0.2.2.dist-info/entry_points.txt
modules_gui-0.2.2.dist-info/top_level.txt
modules_gui-0.2.2.dist-info/RECORD
