Metadata-Version: 2.1
Name: modules-gui
Version: 0.2.2
Summary: MoGui, Graphical User Interface for Modules
Author-email: Xavier Delaruelle <xavier.delaruelle@cea.fr>, Aurélien Cedeyn <aurelien.cedeyn@cea.fr>
License: GNU GENERAL PUBLIC LICENSE
Project-URL: Homepage, https://github.com/cea-hpc/mogui/
Project-URL: Repository, https://github.com/cea-hpc/mogui.git
Project-URL: Issues, https://github.com/cea-hpc/mogui/issues
Classifier: Development Status :: 4 - Beta
Classifier: Environment :: X11 Applications :: Qt
Classifier: Intended Audience :: End Users/Desktop
Classifier: Intended Audience :: Science/Research
Classifier: Intended Audience :: System Administrators
Classifier: License :: OSI Approved :: GNU General Public License v2 or later (GPLv2+)
Classifier: Operating System :: OS Independent
Classifier: Programming Language :: Python :: 3 :: Only
Classifier: Programming Language :: Python :: 3.6
Classifier: Programming Language :: Python :: 3.7
Classifier: Programming Language :: Python :: 3.8
Classifier: Programming Language :: Python :: 3.9
Classifier: Programming Language :: Python :: 3.10
Classifier: Programming Language :: Python :: 3.11
Classifier: Topic :: Scientific/Engineering
Classifier: Topic :: Software Development
Requires-Python: >=3.6
License-File: COPYING-ICONS.CCBYSA3
License-File: COPYING.GPLv2
Requires-Dist: PyQt5
